{
  "2025-11-13": {
    "factors": [
      "Volatility",
      "Trend",
      "Liquidity",
      "Price/Level",
      "Momentum"
    ],
    "exposures": [
      0.0968,
      0.0626,
      0.132,
      -0.181,
      -0.1248
    ],
    "risk_contributions": [
      10.89,
      5.86,
      1.8,
      -1.78,
      -7.07
    ],
    "specific_risk_contribution": 90.3,
    "specific_risk": 0.0136,
    "total_portfolio_variance": 0.00027,
    "pca_variance_explained": {
      "Price/Level": 0.9978675524946833,
      "Trend": 0.728724387801319,
      "Momentum": 0.6238300165520736,
      "Volatility": 0.7290687339858377,
      "Liquidity": 1.0,
      "Custom": 1.0
    }
  },
  "2025-11-14": {
    "factors": [
      "Volatility",
      "Trend",
      "Liquidity",
      "Price/Level",
      "Momentum"
    ],
    "exposures": [
      0.1438,
      0.1494,
      0.0383,
      -0.1174,
      -0.034
    ],
    "risk_contributions": [
      31.99,
      26.2,
      0.72,
      -2.11,
      -3.33
    ],
    "specific_risk_contribution": 46.53,
    "specific_risk": 0.0138,
    "total_portfolio_variance": 0.00021,
    "pca_variance_explained": {
      "Price/Level": 0.9978675524946833,
      "Trend": 0.728724387801319,
      "Momentum": 0.6238300165520736,
      "Volatility": 0.7290687339858377,
      "Liquidity": 1.0,
      "Custom": 1.0
    }
  },
  "2025-11-17": {
    "factors": [
      "Volatility",
      "Trend",
      "Momentum",
      "Liquidity",
      "Price/Level"
    ],
    "exposures": [
      0.2049,
      0.2043,
      0.0695,
      -0.0162,
      -0.0488
    ],
    "risk_contributions": [
      38.64,
      32.81,
      5.05,
      -0.29,
      -0.62
    ],
    "specific_risk_contribution": 24.4,
    "specific_risk": 0.0145,
    "total_portfolio_variance": 0.000266,
    "pca_variance_explained": {
      "Price/Level": 0.9978675524946833,
      "Trend": 0.728724387801319,
      "Momentum": 0.6238300165520736,
      "Volatility": 0.7290687339858377,
      "Liquidity": 1.0,
      "Custom": 1.0
    }
  },
  "2025-11-19": {
    "factors": [
      "Volatility",
      "Price/Level",
      "Momentum",
      "Liquidity",
      "Trend"
    ],
    "exposures": [
      0.1086,
      0.1182,
      0.0331,
      0.0434,
      -0.1204
    ],
    "risk_contributions": [
      0.16,
      0.12,
      0.03,
      0.0,
      -0.06
    ],
    "specific_risk_contribution": 99.73,
    "specific_risk": 0.018,
    "total_portfolio_variance": 0.003388,
    "pca_variance_explained": {
      "Price/Level": 0.9978675524946833,
      "Trend": 0.728724387801319,
      "Momentum": 0.6238300165520736,
      "Volatility": 0.7290687339858377,
      "Liquidity": 1.0,
      "Custom": 1.0
    }
  },
  "2025-11-21": {
    "factors": [
      "Volatility",
      "Trend",
      "Momentum",
      "Price/Level",
      "Liquidity"
    ],
    "exposures": [
      0.2353,
      0.1994,
      0.0122,
      -0.0594,
      -0.1059
    ],
    "risk_contributions": [
      1.74,
      1.42,
      0.01,
      -0.03,
      -0.24
    ],
    "specific_risk_contribution": 97.09,
    "specific_risk": 0.0349,
    "total_portfolio_variance": 0.010034,
    "pca_variance_explained": {
      "Price/Level": 0.9978675524946833,
      "Trend": 0.728724387801319,
      "Momentum": 0.6238300165520736,
      "Volatility": 0.7290687339858377,
      "Liquidity": 1.0,
      "Custom": 1.0
    }
  },
  "2025-11-28": {
    "factors": [
      "Trend",
      "Volatility",
      "Price/Level",
      "Momentum",
      "Liquidity"
    ],
    "exposures": [
      0.0927,
      0.0646,
      0.0126,
      -0.0584,
      -0.0287
    ],
    "risk_contributions": [
      53.04,
      32.83,
      0.79,
      0.49,
      -4.44
    ],
    "specific_risk_contribution": 17.29,
    "specific_risk": 0.0121,
    "total_portfolio_variance": 4.2e-05,
    "pca_variance_explained": {
      "Price/Level": 0.9978675524946833,
      "Trend": 0.728724387801319,
      "Momentum": 0.6238300165520736,
      "Volatility": 0.7290687339858377,
      "Liquidity": 1.0,
      "Custom": 1.0
    }
  },
  "2025-12-01": {
    "factors": [
      "Trend",
      "Volatility",
      "Momentum",
      "Price/Level",
      "Liquidity"
    ],
    "exposures": [
      0.0813,
      0.0661,
      -0.0454,
      0.0181,
      -0.0463
    ],
    "risk_contributions": [
      42.73,
      30.55,
      1.69,
      0.87,
      -5.19
    ],
    "specific_risk_contribution": 29.35,
    "specific_risk": 0.0181,
    "total_portfolio_variance": 3.8e-05,
    "pca_variance_explained": {
      "Price/Level": 0.9978675524946833,
      "Trend": 0.728724387801319,
      "Momentum": 0.6238300165520736,
      "Volatility": 0.7290687339858377,
      "Liquidity": 1.0,
      "Custom": 1.0
    }
  },
  "2025-12-02": {
    "factors": [
      "Volatility",
      "Trend",
      "Price/Level",
      "Momentum",
      "Liquidity"
    ],
    "exposures": [
      0.0709,
      0.0686,
      0.0378,
      -0.0246,
      -0.019
    ],
    "risk_contributions": [
      28.54,
      25.85,
      2.24,
      0.2,
      -1.4
    ],
    "specific_risk_contribution": 44.57,
    "specific_risk": 0.0181,
    "total_portfolio_variance": 4.4e-05,
    "pca_variance_explained": {
      "Price/Level": 0.9978675524946833,
      "Trend": 0.728724387801319,
      "Momentum": 0.6238300165520736,
      "Volatility": 0.7290687339858377,
      "Liquidity": 1.0,
      "Custom": 1.0
    }
  },
  "2025-12-03": {
    "factors": [
      "Volatility",
      "Trend",
      "Momentum",
      "Liquidity",
      "Price/Level"
    ],
    "exposures": [
      0.0695,
      0.0648,
      -0.0545,
      -0.0001,
      -0.0049
    ],
    "risk_contributions": [
      22.16,
      21.28,
      1.33,
      -0.01,
      -0.1
    ],
    "specific_risk_contribution": 55.34,
    "specific_risk": 0.0147,
    "total_portfolio_variance": 4.6e-05,
    "pca_variance_explained": {
      "Price/Level": 0.9978675524946833,
      "Trend": 0.728724387801319,
      "Momentum": 0.6238300165520736,
      "Volatility": 0.7290687339858377,
      "Liquidity": 1.0,
      "Custom": 1.0
    }
  },
  "2025-12-04": {
    "factors": [
      "Volatility",
      "Trend",
      "Price/Level",
      "Momentum",
      "Liquidity"
    ],
    "exposures": [
      0.0423,
      0.0316,
      0.0292,
      -0.0129,
      -0.0022
    ],
    "risk_contributions": [
      22.85,
      14.59,
      2.83,
      0.41,
      -0.16
    ],
    "specific_risk_contribution": 59.5,
    "specific_risk": 0.016,
    "total_portfolio_variance": 1.6e-05,
    "pca_variance_explained": {
      "Price/Level": 0.9978675524946833,
      "Trend": 0.728724387801319,
      "Momentum": 0.6238300165520736,
      "Volatility": 0.7290687339858377,
      "Liquidity": 1.0,
      "Custom": 1.0
    }
  },
  "2025-12-05": {
    "factors": [
      "Volatility",
      "Trend",
      "Price/Level",
      "Momentum",
      "Liquidity"
    ],
    "exposures": [
      0.0403,
      0.0235,
      0.0293,
      -0.0116,
      -0.0026
    ],
    "risk_contributions": [
      11.45,
      5.14,
      1.63,
      0.16,
      -0.07
    ],
    "specific_risk_contribution": 81.69,
    "specific_risk": 0.0152,
    "total_portfolio_variance": 2.5e-05,
    "pca_variance_explained": {
      "Price/Level": 0.9978675524946833,
      "Trend": 0.728724387801319,
      "Momentum": 0.6238300165520736,
      "Volatility": 0.7290687339858377,
      "Liquidity": 1.0,
      "Custom": 1.0
    }
  },
  "2025-12-08": {
    "factors": [
      "Volatility",
      "Price/Level",
      "Trend",
      "Momentum",
      "Liquidity"
    ],
    "exposures": [
      0.0392,
      0.0297,
      0.0078,
      -0.0182,
      -0.001
    ],
    "risk_contributions": [
      32.26,
      4.19,
      2.77,
      1.66,
      0.03
    ],
    "specific_risk_contribution": 59.09,
    "specific_risk": 0.0134,
    "total_portfolio_variance": 8e-06,
    "pca_variance_explained": {
      "Price/Level": 0.9978675524946833,
      "Trend": 0.728724387801319,
      "Momentum": 0.6238300165520736,
      "Volatility": 0.7290687339858377,
      "Liquidity": 1.0,
      "Custom": 1.0
    }
  },
  "2025-12-09": {
    "factors": [
      "Volatility",
      "Price/Level",
      "Momentum",
      "Liquidity",
      "Trend"
    ],
    "exposures": [
      0.0325,
      0.0299,
      -0.0257,
      -0.0021,
      -0.0032
    ],
    "risk_contributions": [
      8.8,
      2.16,
      1.54,
      0.1,
      -0.24
    ],
    "specific_risk_contribution": 87.63,
    "specific_risk": 0.0183,
    "total_portfolio_variance": 1.7e-05,
    "pca_variance_explained": {
      "Price/Level": 0.9978675524946833,
      "Trend": 0.728724387801319,
      "Momentum": 0.6238300165520736,
      "Volatility": 0.7290687339858377,
      "Liquidity": 1.0,
      "Custom": 1.0
    }
  },
  "2025-12-10": {
    "factors": [
      "Trend",
      "Momentum",
      "Price/Level",
      "Liquidity",
      "Volatility"
    ],
    "exposures": [
      0.0341,
      -0.02,
      0.0241,
      0.0043,
      0.0077
    ],
    "risk_contributions": [
      15.01,
      5.99,
      1.46,
      0.27,
      -0.06
    ],
    "specific_risk_contribution": 77.32,
    "specific_risk": 0.0168,
    "total_portfolio_variance": 1.8e-05,
    "pca_variance_explained": {
      "Price/Level": 0.9978675524946833,
      "Trend": 0.728724387801319,
      "Momentum": 0.6238300165520736,
      "Volatility": 0.7290687339858377,
      "Liquidity": 1.0,
      "Custom": 1.0
    }
  },
  "2025-12-11": {
    "factors": [
      "Trend",
      "Volatility",
      "Price/Level",
      "Liquidity",
      "Momentum"
    ],
    "exposures": [
      0.0593,
      0.032,
      0.0216,
      0.0008,
      0.0092
    ],
    "risk_contributions": [
      74.89,
      22.57,
      4.43,
      0.28,
      -2.17
    ],
    "specific_risk_contribution": 0.0,
    "specific_risk": null,
    "total_portfolio_variance": 7e-06,
    "pca_variance_explained": {
      "Price/Level": 0.9978675524946833,
      "Trend": 0.728724387801319,
      "Momentum": 0.6238300165520736,
      "Volatility": 0.7290687339858377,
      "Liquidity": 1.0,
      "Custom": 1.0
    }
  },
  "2025-12-15": {
    "factors": [
      "Trend",
      "Volatility",
      "Momentum",
      "Price/Level",
      "Liquidity"
    ],
    "exposures": [
      0.0565,
      0.0301,
      -0.0165,
      -0.0037,
      -0.0117
    ],
    "risk_contributions": [
      35.2,
      9.77,
      6.84,
      0.85,
      -2.91
    ],
    "specific_risk_contribution": 50.26,
    "specific_risk": 0.0131,
    "total_portfolio_variance": 1.4e-05,
    "pca_variance_explained": {
      "Price/Level": 0.9978675524946833,
      "Trend": 0.728724387801319,
      "Momentum": 0.6238300165520736,
      "Volatility": 0.7290687339858377,
      "Liquidity": 1.0,
      "Custom": 1.0
    }
  },
  "2025-12-16": {
    "factors": [
      "Trend",
      "Volatility",
      "Momentum",
      "Price/Level",
      "Liquidity"
    ],
    "exposures": [
      0.0627,
      0.0308,
      -0.0055,
      0.0107,
      0.002
    ],
    "risk_contributions": [
      0.38,
      0.08,
      0.01,
      0.01,
      0.0
    ],
    "specific_risk_contribution": 99.52,
    "specific_risk": 0.0387,
    "total_portfolio_variance": 0.001524,
    "pca_variance_explained": {
      "Price/Level": 0.9978675524946833,
      "Trend": 0.728724387801319,
      "Momentum": 0.6238300165520736,
      "Volatility": 0.7290687339858377,
      "Liquidity": 1.0,
      "Custom": 1.0
    }
  },
  "2025-12-17": {
    "factors": [
      "Trend",
      "Volatility",
      "Price/Level",
      "Momentum",
      "Liquidity"
    ],
    "exposures": [
      0.079,
      0.0264,
      0.0104,
      -0.0239,
      -0.0136
    ],
    "risk_contributions": [
      28.13,
      7.33,
      2.69,
      1.38,
      -1.54
    ],
    "specific_risk_contribution": 62.01,
    "specific_risk": 0.0145,
    "total_portfolio_variance": 4.2e-05,
    "pca_variance_explained": {
      "Price/Level": 0.9978675524946833,
      "Trend": 0.728724387801319,
      "Momentum": 0.6238300165520736,
      "Volatility": 0.7290687339858377,
      "Liquidity": 1.0,
      "Custom": 1.0
    }
  },
  "2025-12-18": {
    "factors": [
      "Trend",
      "Price/Level",
      "Volatility",
      "Liquidity",
      "Momentum"
    ],
    "exposures": [
      0.0752,
      0.0291,
      0.0294,
      -0.01,
      -0.0138
    ],
    "risk_contributions": [
      29.88,
      16.51,
      13.76,
      -0.7,
      -0.87
    ],
    "specific_risk_contribution": 41.42,
    "specific_risk": 0.019,
    "total_portfolio_variance": 3.9e-05,
    "pca_variance_explained": {
      "Price/Level": 0.9978675524946833,
      "Trend": 0.728724387801319,
      "Momentum": 0.6238300165520736,
      "Volatility": 0.7290687339858377,
      "Liquidity": 1.0,
      "Custom": 1.0
    }
  },
  "2025-12-19": {
    "factors": [
      "Trend",
      "Volatility",
      "Price/Level",
      "Liquidity",
      "Momentum"
    ],
    "exposures": [
      0.0683,
      0.0402,
      0.0302,
      0.0134,
      -0.0179
    ],
    "risk_contributions": [
      29.2,
      28.45,
      16.86,
      2.11,
      -2.15
    ],
    "specific_risk_contribution": 25.53,
    "specific_risk": 0.0323,
    "total_portfolio_variance": 4.4e-05,
    "pca_variance_explained": {
      "Price/Level": 0.9978675524946833,
      "Trend": 0.728724387801319,
      "Momentum": 0.6238300165520736,
      "Volatility": 0.7290687339858377,
      "Liquidity": 1.0,
      "Custom": 1.0
    }
  },
  "2025-12-22": {
    "factors": [
      "Trend",
      "Volatility",
      "Price/Level",
      "Liquidity",
      "Momentum"
    ],
    "exposures": [
      0.0628,
      0.0317,
      0.0192,
      0.0091,
      -0.0208
    ],
    "risk_contributions": [
      38.41,
      29.77,
      13.08,
      2.14,
      -1.47
    ],
    "specific_risk_contribution": 18.07,
    "specific_risk": 0.0101,
    "total_portfolio_variance": 2.4e-05,
    "pca_variance_explained": {
      "Price/Level": 0.9978675524946833,
      "Trend": 0.728724387801319,
      "Momentum": 0.6238300165520736,
      "Volatility": 0.7290687339858377,
      "Liquidity": 1.0,
      "Custom": 1.0
    }
  },
  "2025-12-23": {
    "factors": [
      "Trend",
      "Volatility",
      "Price/Level",
      "Liquidity",
      "Momentum"
    ],
    "exposures": [
      0.0605,
      0.0274,
      0.019,
      0.0076,
      -0.0207
    ],
    "risk_contributions": [
      45.68,
      29.54,
      16.38,
      2.07,
      -1.18
    ],
    "specific_risk_contribution": 7.52,
    "specific_risk": 0.0062,
    "total_portfolio_variance": 1.7e-05,
    "pca_variance_explained": {
      "Price/Level": 0.9978675524946833,
      "Trend": 0.728724387801319,
      "Momentum": 0.6238300165520736,
      "Volatility": 0.7290687339858377,
      "Liquidity": 1.0,
      "Custom": 1.0
    }
  },
  "2025-12-24": {
    "factors": [
      "Trend",
      "Volatility",
      "Price/Level",
      "Liquidity",
      "Momentum"
    ],
    "exposures": [
      0.059,
      0.022,
      0.0188,
      0.0129,
      -0.027
    ],
    "risk_contributions": [
      48.76,
      22.87,
      15.78,
      3.99,
      0.99
    ],
    "specific_risk_contribution": 7.63,
    "specific_risk": 0.0067,
    "total_portfolio_variance": 1.4e-05,
    "pca_variance_explained": {
      "Price/Level": 0.9978675524946833,
      "Trend": 0.728724387801319,
      "Momentum": 0.6238300165520736,
      "Volatility": 0.7290687339858377,
      "Liquidity": 1.0,
      "Custom": 1.0
    }
  },
  "2025-12-26": {
    "factors": [
      "Trend",
      "Price/Level",
      "Momentum",
      "Volatility",
      "Liquidity"
    ],
    "exposures": [
      0.0599,
      0.0147,
      -0.0329,
      0.0105,
      0.0025
    ],
    "risk_contributions": [
      65.79,
      13.9,
      10.59,
      9.01,
      0.71
    ],
    "specific_risk_contribution": 0.0,
    "specific_risk": null,
    "total_portfolio_variance": 9e-06,
    "pca_variance_explained": {
      "Price/Level": 0.9978675524946833,
      "Trend": 0.728724387801319,
      "Momentum": 0.6238300165520736,
      "Volatility": 0.7290687339858377,
      "Liquidity": 1.0,
      "Custom": 1.0
    }
  }
}